README.txt
setup.py
keggrest/__init__.py
keggrest/keggrest.py
keggrest.egg-info/PKG-INFO
keggrest.egg-info/SOURCES.txt
keggrest.egg-info/dependency_links.txt
keggrest.egg-info/top_level.txt