Metadata-Version: 1.1
Name: keggrest
Version: 0.1.1
Summary: Basic frontend for the kegg database rest API
Home-page: https://github.com/EnricoGiampieri/keggrest.git
Author: Enrico Giampieri
Author-email: enrico.giampieri@unibo.it
License: BSD
Download-URL: https://github.com/EnricoGiampieri/keggrest.git
Keywords: rest API bioinformatics
Platform: UNKNOWN
Classifier: License :: OSI Approved :: BSD License
Classifier: Development Status :: 3 - Alpha
Classifier: Intended Audience :: Science/Research
Classifier: Operating System :: OS Independent
Classifier: Programming Language :: Python :: 2.7
Classifier: Topic :: Scientific/Engineering :: Bio-Informatics
